dagger/DaggerAPI.py
dagger/DaggerFunctionWrapper.py
dagger/Task.py
dagger/__init__.py
dagger/config.py
dagger/dream.tmp.py
dagger/logger.py
dagger/test_dagger.py
dagger/integrations/__init__.py
dagger/integrations/aws_ecs.py
dagger/integrations/aws_lambda.py
dagger/integrations/base.py
dagger/integrations/test_aws_ecs.py
python_dagger-0.0.17.dist-info/METADATA
python_dagger-0.0.17.dist-info/WHEEL
python_dagger-0.0.17.dist-info/top_level.txt
python_dagger-0.0.17.dist-info/RECORD
