Metadata-Version: 2.1
Name: python-dagger
Version: 0.0.17
Summary: Api for python
Home-page: https://github.com/dagger-team/python-dagger
Author: Mike Lyons
Author-email: mdl0394@gmail.com
License: MIT
Platform: UNKNOWN
Requires-Dist: requests
